aiogramui/__init__.py
aiogramui/button.py
aiogramui/checkbox.py
aiogramui/custom.py
aiogramui/dialog.py
aiogramui/filters.py
aiogramui/main.py
aiogramui-1.2.0.dist-info/METADATA
aiogramui-1.2.0.dist-info/WHEEL
aiogramui-1.2.0.dist-info/licenses/LICENSE
aiogramui-1.2.0.dist-info/RECORD
