Metadata-Version: 2.4
Name: aiogramui
Version: 1.2.0
Summary: A minimalistic UI framework for aiogram bots.
Project-URL: Homepage, https://github.com/evryoneowo/aiogramui
Project-URL: Repository, https://github.com/evryoneowo/aiogramui
Author-email: evryoneowo <evryhvh@email.com>
License: MIT
License-File: LICENSE
Requires-Python: >=3.9
Requires-Dist: aiogram>=3.0.0
